PIP_procedure
README.md
VERSION
setup.py
eigenmorphic/IET.py
eigenmorphic/__init__.py
eigenmorphic/balanced_pair_algo.py
eigenmorphic/coboundary.py
eigenmorphic/eigenvalues.py
eigenmorphic/matrix.py
eigenmorphic/rauzy_fractal.py
eigenmorphic/recognizability.py
eigenmorphic.egg-info/PKG-INFO
eigenmorphic.egg-info/SOURCES.txt
eigenmorphic.egg-info/dependency_links.txt
eigenmorphic.egg-info/top_level.txt