Metadata-Version: 2.1
Name: eigenmorphic
Version: 0.2.6
Summary: Eigenvalues of morphic subshifts
Home-page: https://gitlab.com/mercatp/eigenmorphic
Author: Paul Mercat
Author-email: paul.mercat@univ-amu.fr
License: GPLv3.0
Keywords: SageMath Eigenvalue Substitutive Morphic Subshift
Classifier: Development Status :: 4 - Beta
Classifier: Intended Audience :: Science/Research
Classifier: Topic :: Software Development :: Build Tools
Classifier: Topic :: Scientific/Engineering :: Mathematics
Classifier: License :: OSI Approved :: GNU General Public License v3 or later (GPLv3+)
Classifier: Programming Language :: Python :: 2.7
